ilkbyte_cli/__init__.py
ilkbyte_cli/account.py
ilkbyte_cli/backup.py
ilkbyte_cli/callback.py
ilkbyte_cli/domain.py
ilkbyte_cli/main.py
ilkbyte_cli/server.py
ilkbyte_cli/snapshot.py
ilkbyte_cli/utils.py
ilkbyte_cli-1.0.3.dist-info/LICENSE
ilkbyte_cli-1.0.3.dist-info/METADATA
ilkbyte_cli-1.0.3.dist-info/WHEEL
ilkbyte_cli-1.0.3.dist-info/entry_points.txt
ilkbyte_cli-1.0.3.dist-info/top_level.txt
ilkbyte_cli-1.0.3.dist-info/RECORD
