Metadata-Version: 2.1
Name: ilkbyte-cli
Version: 1.0.3
Summary: Ilkbyte python CLI
Home-page: https://github.com/bkayranci/ilkbyte-cli
Author: Türkalp Burak Kayrancıoğlu
Author-email: bkayranci@gmail.com
License: UNKNOWN
Platform: UNKNOWN
Classifier: Programming Language :: Python :: 3
Classifier: License :: OSI Approved :: MIT License
Classifier: Operating System :: OS Independent
Requires-Python: >=3.6
Requires-Dist: typer (==0.3.2)
Requires-Dist: ilkbyte (==1.0.2)
Requires-Dist: tabulate (==0.8.7)
Requires-Dist: dotty-dict (==1.3.0)
